keyrings/__init__.py
keyrings/alt/Gnome.py
keyrings/alt/Google.py
keyrings/alt/Windows.py
keyrings/alt/__init__.py
keyrings/alt/_win_crypto.py
keyrings/alt/escape.py
keyrings/alt/file.py
keyrings/alt/file_base.py
keyrings/alt/keyczar.py
keyrings/alt/multi.py
keyrings.alt-5.0.1.dist-info/LICENSE
keyrings.alt-5.0.1.dist-info/METADATA
keyrings.alt-5.0.1.dist-info/WHEEL
keyrings.alt-5.0.1.dist-info/entry_points.txt
keyrings.alt-5.0.1.dist-info/top_level.txt
keyrings.alt-5.0.1.dist-info/RECORD
