Metadata-Version: 2.1
Name: keyrings.alt
Version: 5.0.1
Summary: Alternate keyring implementations
Home-page: https://github.com/jaraco/keyrings.alt
Author: Jason R. Coombs
Author-email: jaraco@jaraco.com
Classifier: Development Status :: 5 - Production/Stable
Classifier: Intended Audience :: Developers
Classifier: License :: OSI Approved :: MIT License
Classifier: Programming Language :: Python :: 3
Classifier: Programming Language :: Python :: 3 :: Only
Requires-Python: >=3.8
License-File: LICENSE
Requires-Dist: jaraco.classes
Requires-Dist: jaraco.context
Provides-Extra: testing
Requires-Dist: pytest!=8.1.1,>=6; extra == "testing"
Requires-Dist: pytest-checkdocs>=2.4; extra == "testing"
Requires-Dist: pytest-cov; extra == "testing"
Requires-Dist: pytest-mypy; extra == "testing"
Requires-Dist: pytest-enabler>=2.2; extra == "testing"
Requires-Dist: pytest-ruff>=0.2.1; extra == "testing"
Requires-Dist: backports.unittest_mock; extra == "testing"
Requires-Dist: keyring>=20; extra == "testing"
Requires-Dist: pycryptodomex; extra == "testing"
Requires-Dist: pycryptodome; extra == "testing"
Requires-Dist: gdata; python_version == "2.7" and extra == "testing"
Requires-Dist: python-keyczar; python_version == "2.7" and extra == "testing"
Provides-Extra: docs
Requires-Dist: sphinx>=3.5; extra == "docs"
Requires-Dist: jaraco.packaging>=9.3; extra == "docs"
Requires-Dist: rst.linker>=1.9; extra == "docs"
Requires-Dist: furo; extra == "docs"
Requires-Dist: sphinx-lint; extra == "docs"
Requires-Dist: jaraco.tidelift>=1.4; extra == "docs"
